mayan_edms-1.0.rc2.dist-info/metadata.json
mayan_edms-1.0.rc2.dist-info/DESCRIPTION.rst
mayan_edms-1.0.rc2.dist-info/top_level.txt
mayan_edms-1.0.rc2.dist-info/METADATA
mayan_edms-1.0.rc2.dist-info/RECORD
mayan_edms-1.0.rc2.dist-info/WHEEL
mayan/urls.py
mayan/wsgi.py
mayan/__init__.py
mayan/media/README
mayan/apps/metadata/cleanup.py
mayan/apps/metadata/admin.py
mayan/apps/metadata/models.py
mayan/apps/metadata/permissions.py
mayan/apps/metadata/api.py
mayan/apps/metadata/forms.py
mayan/apps/metadata/registry.py
mayan/apps/metadata/urls.py
mayan/apps/metadata/managers.py
mayan/apps/metadata/__init__.py
mayan/apps/metadata/links.py
mayan/apps/metadata/views.py
mayan/apps/metadata/classes.py
mayan/apps/metadata/conf/settings.py
mayan/apps/metadata/conf/__init__.py
mayan/apps/metadata/migrations/0003_auto__chg_field_metadatatype_lookup.py
mayan/apps/metadata/migrations/__init__.py
mayan/apps/metadata/migrations/0001_initial.py
mayan/apps/metadata/migrations/0002_auto__add_unique_metadataset_title.py
mayan/apps/metadata/static/images/icons/table.png
mayan/apps/metadata/static/images/icons/xhtml.png
mayan/apps/metadata/templates/metadata_type_help.html
mayan/apps/metadata/templates/metadata_set_help.html
mayan/apps/installation/models.py
mayan/apps/installation/permissions.py
mayan/apps/installation/urls.py
mayan/apps/installation/literals.py
mayan/apps/installation/__init__.py
mayan/apps/installation/links.py
mayan/apps/installation/views.py
mayan/apps/installation/classes.py
mayan/apps/installation/migrations/0002_auto__del_field_installation_lock_id.py
mayan/apps/installation/migrations/__init__.py
mayan/apps/installation/migrations/0001_initial.py
mayan/apps/installation/static/images/icons/interface_preferences.png
mayan/apps/web_theme/models.py
mayan/apps/web_theme/__init__.py
mayan/apps/web_theme/views.py
mayan/apps/web_theme/conf/settings.py
mayan/apps/web_theme/conf/__init__.py
mayan/apps/web_theme/templatetags/styling.py
mayan/apps/web_theme/templatetags/__init__.py
mayan/apps/web_theme/templatetags/theme_tags.py
mayan/apps/web_theme/static/packages/animate-custom.css
mayan/apps/web_theme/static/packages/jquery-2.1.1.min.js
