Metadata-Version: 2.0
Name: mayan-edms
Version: 1.0.rc2
Summary: A Django based Document Management System.
Home-page: https://github.com/mayan-edms/mayan-edms
Author: Roberto Rosario
Author-email: roberto.rosario@mayan-edms.com
License: Copyright 2011 Roberto Rosario
Requires-Dist: APScheduler (==2.1.2)
Requires-Dist: cssmin (==0.2.0)
Requires-Dist: Django (==1.6.5)
Requires-Dist: django-filetransfers (==0.1.0)
Requires-Dist: django-pagination (==1.0.7)
Requires-Dist: django-compressor (==1.4)
Requires-Dist: django-taggit (==0.12)
Requires-Dist: django-mptt (==0.6.1)
Requires-Dist: django-rest-swagger (==0.1.14)
Requires-Dist: django-sendfile (==0.3.6)
Requires-Dist: django-solo (==1.0.5)
Requires-Dist: djangorestframework (==2.3.14)
Requires-Dist: GitPython (==0.3.2.RC1)
Requires-Dist: ghostscript (==0.4.1)
Requires-Dist: Pillow (==2.5.0)
Requires-Dist: PyYAML (==3.11)
Requires-Dist: pdfminer (==20110227)
Requires-Dist: psutil (==2.1.1)
Requires-Dist: pytz (==2014.4)
Requires-Dist: python-gnupg (==0.3.6)
Requires-Dist: python-hkp (==0.1.3)
Requires-Dist: python-magic (==0.4.6)
Requires-Dist: requests (==2.3.0)
Requires-Dist: sh (==1.09)
Requires-Dist: slate (==0.3)
Requires-Dist: South (==1.0)
Requires-Dist: unicode-slugify (==0.1)
Requires-Dist: wsgiref (==0.1.2)
